pynrp/__init__.py
pynrp/config.json
pynrp/config.py
pynrp/requests_client.py
pynrp/rosbridge_handler.py
pynrp/simulation.py
pynrp/version.py
pynrp/virtual_coach.py
pynrp-3.2.1.post3.dist-info/METADATA
pynrp-3.2.1.post3.dist-info/WHEEL
pynrp-3.2.1.post3.dist-info/top_level.txt
pynrp-3.2.1.post3.dist-info/RECORD
