Metadata-Version: 2.1
Name: pynrp
Version: 3.2.1.post3
Summary: Python interface to the Neurorobotics Platform (NRP)
Home-page: http://neurorobotics.net
Author: HBP Neurorobotics
Author-email: neurorobotics@humanbrainproject.eu
License: UNKNOWN
Platform: UNKNOWN
Classifier: Programming Language :: Python :: 3.8
Classifier: Programming Language :: Python :: 3.9
Classifier: Programming Language :: Python :: 3.10
Requires-Dist: future
Requires-Dist: httplib2 (==0.12.1)
Requires-Dist: ipykernel (==5.3.2)
Requires-Dist: jupyter (==1.0.0)
Requires-Dist: mechanize
Requires-Dist: pandas (==1.4.4)
Requires-Dist: progressbar2 (==3.52.1)
Requires-Dist: requests
Requires-Dist: roslibpy (==1.1.0)
Requires-Dist: service-identity
Requires-Dist: texttable (==0.8.7)
